{
    "UserAgent": "aws-amplify-cli/2.0",
    "Version": "1.0",
    "auth": {
        "plugins": {
            "awsCognitoAuthPlugin": {
                "UserAgent": "aws-amplify/cli",
                "Version": "0.1.0",
                "IdentityManager": {
                    "Default": {}
                },
                "CredentialsProvider": {
                    "CognitoIdentity": {
                        "Default": {
                            "PoolId": "us-east-2:f5207b84-7f01-440a-92f1-c7fe419aaa48",
                            "Region": "us-east-2"
                        }
                    }
                },
                "CognitoUserPool": {
                    "Default": {
                        "PoolId": "us-east-2_E1xjdssbc",
                        "AppClientId": "2qvihh1ko6sojf1la9mg4t4ck6",
                        "Region": "us-east-2"
                    }
                },
                "Auth": {
                    "Default": {
                        "authenticationFlowType": "USER_SRP_AUTH",
                        "socialProviders": [],
                        "usernameAttributes": [
                            "EMAIL"
                        ],
                        "signupAttributes": [
                            "EMAIL"
                        ],
                        "passwordProtectionSettings": {
                            "passwordPolicyMinLength": 8,
                            "passwordPolicyCharacters": []
                        },
                        "mfaConfiguration": "OFF",
                        "mfaTypes": [
                            "SMS"
                        ],
                        "verificationMechanisms": [
                            "EMAIL"
                        ]
                    }
                },
                "S3TransferUtility": {
                    "Default": {
                        "Bucket": "mapimagesdata",
                        "Region": "us-east-2"
                    }
                }
            }
        }
    },
    "storage": {
        "plugins": {
            "awsS3StoragePlugin": {
                "bucket": "mapimagesdata",
                "region": "us-east-2",
                "defaultAccessLevel": "guest"
            }
        }
    }
}
